MANIFEST.in
README.md
setup.py
chat/__init__.py
chat/admin.py
chat/apps.py
chat/main.py
chat/models.py
chat/tests.py
chat/urls.py
chat/views.py
chat/migrations/0001_initial.py
chat/migrations/0002_auto_20191021_1143.py
chat/migrations/0003_auto_20191021_1225.py
chat/migrations/0004_auto_20191021_1226.py
chat/migrations/0005_remove_chat_admin.py
chat/migrations/0006_chat_uuid.py
chat/migrations/0007_auto_20191021_1708.py
chat/migrations/0008_auto_20191021_1720.py
chat/migrations/0009_auto_20191021_1722.py
chat/migrations/0010_auto_20191021_1735.py
chat/migrations/0011_remove_chatmessage_status.py
chat/migrations/__init__.py
chat/static/admin/css/chat.css
chat/static/admin/js/chat.js
chat/templates/admin/chat.html
chat/templates/admin/chat_changelist.html
django_admin_chat.egg-info/PKG-INFO
django_admin_chat.egg-info/SOURCES.txt
django_admin_chat.egg-info/dependency_links.txt
django_admin_chat.egg-info/top_level.txt